toolbox_store/__init__.py
toolbox_store/data_loaders.py
toolbox_store/db.py
toolbox_store/embedding.py
toolbox_store/embedding_worker.py
toolbox_store/filters.py
toolbox_store/models.py
toolbox_store/ollama_client.py
toolbox_store/query_builder.py
toolbox_store/reranking.py
toolbox_store/store.py
toolbox_store/utils.py
toolbox_store/vector_cache.py
toolbox_store-0.1.1.dist-info/WHEEL
toolbox_store-0.1.1.dist-info/METADATA
toolbox_store-0.1.1.dist-info/RECORD
